CODE_OF_CONDUCT.md
CONTRIBUTING.md
LICENSE
MANIFEST.in
NOTICE
README.md
setup.cfg
setup.py
MXFusion.egg-info/PKG-INFO
MXFusion.egg-info/SOURCES.txt
MXFusion.egg-info/dependency_links.txt
MXFusion.egg-info/requires.txt
MXFusion.egg-info/top_level.txt
mxfusion/__init__.py
mxfusion/__version__.py
mxfusion/common/__init__.py
mxfusion/common/config.py
mxfusion/common/constants.py
mxfusion/common/exceptions.py
mxfusion/components/__init__.py
mxfusion/components/factor.py
mxfusion/components/model_component.py
mxfusion/components/distributions/__init__.py
mxfusion/components/distributions/bernoulli.py
mxfusion/components/distributions/beta.py
mxfusion/components/distributions/categorical.py
mxfusion/components/distributions/dirichlet.py
mxfusion/components/distributions/distribution.py
mxfusion/components/distributions/gamma.py
mxfusion/components/distributions/laplace.py
mxfusion/components/distributions/normal.py
mxfusion/components/distributions/pointmass.py
mxfusion/components/distributions/random_gen.py
mxfusion/components/distributions/uniform.py
mxfusion/components/distributions/univariate.py
mxfusion/components/distributions/wishart.py
mxfusion/components/distributions/gp/__init__.py
mxfusion/components/distributions/gp/cond_gp.py
mxfusion/components/distributions/gp/gp.py
mxfusion/components/distributions/gp/kernels/__init__.py
mxfusion/components/distributions/gp/kernels/add_kernel.py
mxfusion/components/distributions/gp/kernels/kernel.py
mxfusion/components/distributions/gp/kernels/linear.py
mxfusion/components/distributions/gp/kernels/matern.py
mxfusion/components/distributions/gp/kernels/multiply_kernel.py
mxfusion/components/distributions/gp/kernels/rbf.py
mxfusion/components/distributions/gp/kernels/static.py
mxfusion/components/distributions/gp/kernels/stationary.py
mxfusion/components/functions/__init__.py
mxfusion/components/functions/function_evaluation.py
mxfusion/components/functions/gluon_func_eval.py
mxfusion/components/functions/mxfusion_function.py
mxfusion/components/functions/mxfusion_gluon_function.py
mxfusion/components/functions/operators/__init__.py
